Registry/Registry.py
Registry/RegistryLog.py
Registry/RegistryParse.py
Registry/SettingsParse.py
Registry/__init__.py
python_registry-1.3.1.dist-info/METADATA
python_registry-1.3.1.dist-info/RECORD
python_registry-1.3.1.dist-info/WHEEL
python_registry-1.3.1.dist-info/top_level.txt
