Metadata-Version: 2.1
Name: python-registry
Version: 1.3.1
Summary: Read access to Windows Registry files.
Home-page: http://www.williballenthin.com/registry/
Author: Willi Ballenthin
Author-email: willi.ballenthin@gmail.com
License: Apache License (2.0)
Platform: UNKNOWN
Classifier: Programming Language :: Python
Classifier: Programming Language :: Python :: 3
Classifier: Operating System :: OS Independent
Classifier: License :: OSI Approved :: Apache Software License
Requires-Dist: enum-compat
Requires-Dist: unicodecsv
